audiotools/__init__.py
audiotools/post.py
audiotools/preference.py
audiotools/core/__init__.py
audiotools/core/audio_signal.py
audiotools/core/display.py
audiotools/core/dsp.py
audiotools/core/effects.py
audiotools/core/ffmpeg.py
audiotools/core/loudness.py
audiotools/core/playback.py
audiotools/core/util.py
audiotools/core/whisper.py
audiotools/core/templates/__init__.py
audiotools/core/templates/headers.html
audiotools/core/templates/pandoc.css
audiotools/core/templates/widget.html
audiotools/data/__init__.py
audiotools/data/datasets.py
audiotools/data/preprocess.py
audiotools/data/transforms.py
audiotools/metrics/__init__.py
audiotools/metrics/distance.py
audiotools/metrics/quality.py
audiotools/metrics/spectral.py
audiotools/ml/__init__.py
audiotools/ml/accelerator.py
audiotools/ml/decorators.py
audiotools/ml/experiment.py
audiotools/ml/layers/__init__.py
audiotools/ml/layers/base.py
audiotools/ml/layers/spectral_gate.py
descript_audiotools-0.7.2.dist-info/METADATA
descript_audiotools-0.7.2.dist-info/WHEEL
descript_audiotools-0.7.2.dist-info/top_level.txt
descript_audiotools-0.7.2.dist-info/RECORD
