Metadata-Version: 2.1
Name: descript-audiotools
Version: 0.7.2
Summary: Utilities for handling audio.
Author: Prem Seetharaman, Lucas Gestin
Author-email: prem@descript.com
License: MIT
Classifier: Intended Audience :: Developers
Classifier: Intended Audience :: Education
Classifier: Intended Audience :: Science/Research
Classifier: Natural Language :: English
Classifier: Programming Language :: Python :: 3.7
Classifier: Topic :: Artistic Software
Classifier: Topic :: Multimedia
Classifier: Topic :: Multimedia :: Sound/Audio
Classifier: Topic :: Multimedia :: Sound/Audio :: Editors
Classifier: Topic :: Software Development :: Libraries
Provides-Extra: tests
Provides-Extra: docs
Provides-Extra: whisper
